[
  {
    "symbol": "XPL",
    "name": "Plasma",
    "category": "L1",
    "tge_date": "2025-06-15",
    "tge_fdv": 12970000000,
    "current_fdv": 1310000000,
    "vc_total_raised": 0,
    "lead_investors": "Self-funded",
    "fdv_change_pct": -89.9,
    "chain": "plasma",
    "coingecko_id": "plasma-network"
  },
  {
    "symbol": "FF",
    "name": "Falcon Finance",
    "category": "DeFi",
    "tge_date": "2025-07-01",
    "tge_fdv": 6700000000,
    "current_fdv": 949700000,
    "vc_total_raised": 0,
    "lead_investors": "Unknown",
    "fdv_change_pct": -85.8,
    "chain": "ethereum",
    "coingecko_id": "falcon-finance"
  },
  {
    "symbol": "OG",
    "name": "OG",
    "category": "Social",
    "tge_date": "2025-05-20",
    "tge_fdv": 4900000000,
    "current_fdv": 763600000,
    "vc_total_raised": 0,
    "lead_investors": "Unknown",
    "fdv_change_pct": -84.4,
    "chain": "ethereum",
    "coingecko_id": null
  },
  {
    "symbol": "BERA",
    "name": "Berachain",
    "category": "L1",
    "tge_date": "2025-02-06",
    "tge_fdv": 4460000000,
    "current_fdv": 305000000,
    "vc_total_raised": 142000000,
    "lead_investors": "Polychain Capital, Hack VC, Framework Ventures, Brevan Howard Digital",
    "fdv_change_pct": -93.2,
    "total_supply": 500000000,
    "initial_circ_pct": 21.5,
    "chain": "berachain",
    "coingecko_id": "berachain-bera"
  },
  {
    "symbol": "IP",
    "name": "Story Protocol",
    "category": "Infra",
    "tge_date": "2025-02-13",
    "tge_fdv": 2500000000,
    "current_fdv": 1200000000,
    "vc_total_raised": 140000000,
    "lead_investors": "a16z, Polychain Capital",
    "fdv_change_pct": -52.0,
    "total_supply": 1000000000,
    "initial_circ_pct": 25.0,
    "chain": "story",
    "coingecko_id": "story-protocol"
  },
  {
    "symbol": "BIO",
    "name": "Bio Protocol",
    "category": "DeSci",
    "tge_date": "2025-01-03",
    "tge_fdv": 2060000000,
    "current_fdv": 143000000,
    "vc_total_raised": 33000000,
    "lead_investors": "Binance Labs, 1kx",
    "fdv_change_pct": -93.1,
    "total_supply": 3320000000,
    "initial_circ_pct": 8.0,
    "chain": "ethereum",
    "coingecko_id": "bio-protocol"
  },
  {
    "symbol": "XAN",
    "name": "Anoma",
    "category": "Infra",
    "tge_date": "2025-08-01",
    "tge_fdv": 1600000000,
    "current_fdv": 156200000,
    "vc_total_raised": 57750000,
    "lead_investors": "Polychain Capital, Electric Capital",
    "fdv_change_pct": -90.2,
    "chain": "anoma",
    "coingecko_id": null
  },
  {
    "symbol": "PLUME",
    "name": "Plume Network",
    "category": "RWA",
    "tge_date": "2025-04-01",
    "tge_fdv": 1300000000,
    "current_fdv": 158000000,
    "vc_total_raised": 20000000,
    "lead_investors": "Haun Ventures, Galaxy Digital",
    "fdv_change_pct": -87.8,
    "chain": "plume",
    "coingecko_id": "plume-network"
  },
  {
    "symbol": "WAL",
    "name": "Walrus",
    "category": "Infra",
    "tge_date": "2025-03-27",
    "tge_fdv": 2000000000,
    "current_fdv": 1100000000,
    "vc_total_raised": 140000000,
    "lead_investors": "a16z, Standard Crypto",
    "fdv_change_pct": -45.0,
    "chain": "sui",
    "coingecko_id": "walrus-2"
  },
  {
    "symbol": "MON",
    "name": "Monad",
    "category": "L1",
    "tge_date": "2025-11-24",
    "tge_fdv": 2500000000,
    "current_fdv": null,
    "vc_total_raised": 225000000,
    "lead_investors": "Paradigm, Electric Capital",
    "fdv_change_pct": null,
    "total_supply": 100000000000,
    "initial_circ_pct": null,
    "chain": "monad",
    "coingecko_id": "monad"
  },
  {
    "symbol": "KAITO",
    "name": "Kaito AI",
    "category": "AI",
    "tge_date": "2025-02-20",
    "tge_fdv": 1200000000,
    "current_fdv": 350000000,
    "vc_total_raised": 10800000,
    "lead_investors": "Sequoia Capital, Dragonfly Capital",
    "fdv_change_pct": -70.8,
    "total_supply": 1000000000,
    "initial_circ_pct": 24.1,
    "chain": "base",
    "coingecko_id": "kaito"
  },
  {
    "symbol": "SYND",
    "name": "Syndicate",
    "category": "Infra",
    "tge_date": "2025-09-01",
    "tge_fdv": 940000000,
    "current_fdv": 59800000,
    "vc_total_raised": 27000000,
    "lead_investors": "a16z",
    "fdv_change_pct": -93.6,
    "chain": "ethereum",
    "coingecko_id": null
  },
  {
    "symbol": "ANIME",
    "name": "Animecoin",
    "category": "Consumer",
    "tge_date": "2025-02-05",
    "tge_fdv": 870000000,
    "current_fdv": 55700000,
    "vc_total_raised": 50000000,
    "lead_investors": "Animoca Brands, Azuki",
    "fdv_change_pct": -93.6,
    "total_supply": 10000000000,
    "initial_circ_pct": 5.0,
    "chain": "ethereum",
    "coingecko_id": "animecoin"
  },
  {
    "symbol": "NIL",
    "name": "Nillion",
    "category": "Infra",
    "tge_date": "2025-03-24",
    "tge_fdv": 720000000,
    "current_fdv": 63300000,
    "vc_total_raised": 50000000,
    "lead_investors": "Hack VC, Distributed Global",
    "fdv_change_pct": -91.2,
    "total_supply": 1000000000,
    "initial_circ_pct": 19.5,
    "chain": "nillion",
    "coingecko_id": "nillion"
  },
  {
    "symbol": "TOWNS",
    "name": "Towns",
    "category": "Social",
    "tge_date": "2025-08-15",
    "tge_fdv": 691800000,
    "current_fdv": 60700000,
    "vc_total_raised": 25500000,
    "lead_investors": "a16z, Benchmark",
    "fdv_change_pct": -91.2,
    "chain": "base",
    "coingecko_id": null
  },
  {
    "symbol": "TREE",
    "name": "Tree",
    "category": "DeFi",
    "tge_date": "2025-07-10",
    "tge_fdv": 670000000,
    "current_fdv": 71400000,
    "vc_total_raised": 0,
    "lead_investors": "Unknown",
    "fdv_change_pct": -89.3,
    "chain": "ethereum",
    "coingecko_id": null
  },
  {
    "symbol": "CAMP",
    "name": "Camp Network",
    "category": "Infra",
    "tge_date": "2025-06-20",
    "tge_fdv": 637000000,
    "current_fdv": 69400000,
    "vc_total_raised": 30000000,
    "lead_investors": "1kx, OKX Ventures",
    "fdv_change_pct": -89.1,
    "chain": "camp",
    "coingecko_id": null
  },
  {
    "symbol": "INIT",
    "name": "Initia",
    "category": "Infra",
    "tge_date": "2025-04-24",
    "tge_fdv": 600000000,
    "current_fdv": null,
    "vc_total_raised": 14000000,
    "lead_investors": "Binance Labs, Delphi Ventures",
    "fdv_change_pct": null,
    "chain": "initia",
    "coingecko_id": "initia"
  },
  {
    "symbol": "MOVE",
    "name": "Movement",
    "category": "L1",
    "tge_date": "2025-01-09",
    "tge_fdv": 800000000,
    "current_fdv": null,
    "vc_total_raised": 41400000,
    "lead_investors": "Polychain Capital, Hack VC",
    "fdv_change_pct": null,
    "chain": "movement",
    "coingecko_id": "movement"
  },
  {
    "symbol": "XTER",
    "name": "Xterio",
    "category": "Gaming",
    "tge_date": "2025-02-20",
    "tge_fdv": 420000000,
    "current_fdv": 30000000,
    "vc_total_raised": 55000000,
    "lead_investors": "Binance Labs, FunPlus",
    "fdv_change_pct": -92.9,
    "chain": "xter",
    "coingecko_id": "xterio"
  },
  {
    "symbol": "YALA",
    "name": "Yala",
    "category": "DeFi",
    "tge_date": "2025-09-15",
    "tge_fdv": 240000000,
    "current_fdv": 20100000,
    "vc_total_raised": 8000000,
    "lead_investors": "Polychain Capital, Ethereal Ventures",
    "fdv_change_pct": -91.6,
    "chain": "bitcoin",
    "coingecko_id": null
  },
  {
    "symbol": "LITKEY",
    "name": "Lit Protocol",
    "category": "Infra",
    "tge_date": "2025-08-20",
    "tge_fdv": 210000000,
    "current_fdv": 16700000,
    "vc_total_raised": 18000000,
    "lead_investors": "1kx, Blockchain Capital",
    "fdv_change_pct": -92.1,
    "chain": "ethereum",
    "coingecko_id": null
  },
  {
    "symbol": "EPT",
    "name": "Balance",
    "category": "Gaming",
    "tge_date": "2025-03-15",
    "tge_fdv": 170000000,
    "current_fdv": 16000000,
    "vc_total_raised": 12000000,
    "lead_investors": "a16z GAMES, Animoca Brands",
    "fdv_change_pct": -90.6,
    "chain": "ethereum",
    "coingecko_id": null
  },
  {
    "symbol": "HMND",
    "name": "Humanity Protocol",
    "category": "Infra",
    "tge_date": "2025-05-01",
    "tge_fdv": 400000000,
    "current_fdv": null,
    "vc_total_raised": 30000000,
    "lead_investors": "Kingsway Capital, Animoca Brands",
    "fdv_change_pct": null,
    "chain": "polygon",
    "coingecko_id": "humanity-protocol"
  },
  {
    "symbol": "ABSTRACT",
    "name": "Abstract Chain",
    "category": "L2",
    "tge_date": "2025-01-27",
    "tge_fdv": 300000000,
    "current_fdv": null,
    "vc_total_raised": 11000000,
    "lead_investors": "1kx, Igloo (Pudgy Penguins)",
    "fdv_change_pct": null,
    "chain": "abstract",
    "coingecko_id": null
  },
  {
    "symbol": "ASTER",
    "name": "Aster DEX",
    "category": "Perp DEX",
    "tge_date": "2025-09-17",
    "tge_fdv": 50000000,
    "current_fdv": 400000000,
    "vc_total_raised": 0,
    "lead_investors": "YZi Labs (Binance Labs), CZ backed",
    "fdv_change_pct": 700.0,
    "chain": "bnb",
    "coingecko_id": "aster-dex",
    "note": "Best performer of 2025 TGEs, +700% from TGE"
  },
  {
    "symbol": "ZORA",
    "name": "Zora",
    "category": "Consumer",
    "tge_date": "2025-04-23",
    "tge_fdv": null,
    "current_fdv": null,
    "vc_total_raised": 60000000,
    "lead_investors": "Haun Ventures, Coinbase Ventures",
    "fdv_change_pct": null,
    "chain": "zora",
    "coingecko_id": "zora",
    "note": "One of the few 'green' tokens"
  },
  {
    "symbol": "BEDROCK",
    "name": "Bedrock",
    "category": "DeFi",
    "tge_date": "2025-05-01",
    "tge_fdv": null,
    "current_fdv": null,
    "vc_total_raised": 8000000,
    "lead_investors": "OKX Ventures, Amber Group",
    "fdv_change_pct": null,
    "chain": "ethereum",
    "coingecko_id": "bedrock-defi",
    "note": "Green — maintained value post-TGE"
  }
]